xray_disease_detector.py
xray_disease_detector-0.1.2.dist-info/METADATA
xray_disease_detector-0.1.2.dist-info/WHEEL
xray_disease_detector-0.1.2.dist-info/entry_points.txt
xray_disease_detector-0.1.2.dist-info/top_level.txt
xray_disease_detector-0.1.2.dist-info/RECORD
